[
    {
    "type": "GENERIC",
    "id": "battletorch_done",
    "name": { "str": "ルイビルスロータラー(使用済)" },
    "description": "耐熱性のノーメックス生地で覆った木製バットです。このままでも丁度いい近接武器になりますが、分解する事でより優れた野球バットとノーメックスの布片へと再利用できます。",
    "weight": "1343 g",
    "to_hit": 3,
    "color": "brown",
    "symbol": "/",
    "material": [ "wood" ],
    "techniques": [ "WBLOCK_1" ],
    "flags": [ "DURABLE_MELEE" ],
    "volume": "1750 ml",
    "bashing": 19,
    "price": 18000
  },
  {
    "type": "GENERIC",
    "id": "i_staff",
    "symbol": "/",
    "color": "brown",
    "looks_like": "q_staff",
    "name": { "str": "ironshod quarterstaff", "str_pl": "ironshod quarterstaves" },
    "description": "A smooth and sturdy staff with a leather-wrapped grip, which has been reinforced with metal bands and caps.  Durable and well-balanced, it is surprisingly easy to handle.",
    "price": 6000,
    "price_postapoc": 1500,
    "material": [ "wood", "iron" ],
    "techniques": [ "WBLOCK_2", "RAPID", "SWEEP" ],
    "flags": [ "NONCONDUCTIVE", "SHEATH_SPEAR", "ALWAYS_TWOHAND","DURABLE_MELEE" ],
    "weapon_category": [ "QUARTERSTAVES" ],
    "weight": "1750 g",
    "volume": "1550 ml",
    "longest_side": "180 cm",
    "bashing": 32,
    "to_hit": { "grip": "weapon", "length": "long", "surface": "any", "balance": "good" },
    "category": "weapons",
    "qualities": [ [ "HAMMER", 1 ] ]
  },
  {
    "type": "GENERIC",
    "id": "q_staff",
    "symbol": "/",
    "color": "brown",
    "name": { "str": "quarterstaff", "str_pl": "quarterstaves" },
    "description": "A smooth and sturdy staff.  Light and well-balanced, it is surprisingly easy to handle.",
    "price": 4000,
    "material": [ "wood" ],
    "techniques": [ "WBLOCK_2", "RAPID", "SWEEP" ],
    "flags": [ "SHEATH_SPEAR", "ALWAYS_TWOHAND","DURABLE_MELEE" ],
    "weapon_category": [ "QUARTERSTAVES" ],
    "weight": "1500 g",
    "volume": "1500 ml",
    "longest_side": "180 cm",
    "bashing": 26,
    "category": "weapons",
    "to_hit": { "grip": "weapon", "length": "long", "surface": "any", "balance": "good" },
    "price_postapoc": 1000
  }
]
