[
  {
    "id": "tihar",
    "looks_like": "ar15",
    "type": "GUN",
    "longest_side": "800 mm",
    "reload_noise_volume": 10,
    "symbol": "(",
    "color": "light_gray",
    "name": { "str_sp": "ライフル(石つぶて/空圧式ｱｻﾙﾄﾗｲﾌﾙ)" },
    "description": "スクラップから自作した多工程の空圧式ライフルです。とても静かで高い殺傷力があります。",
    "price": 240000,
    "price_postapoc": 12000,
    "material": [ "steel", "wood" ],
    "flags": [ "STR_RELOAD", "RELOAD_ONE", "NON_FOULING" ],
    "skill": "rifle",
    "ammo": [ "pebble" ],
    "weight": "4211 g",
    "volume": "2750 ml",
    "melee_damage": { "bash": 8 },
    "to_hit": -1,
    "ranged_damage": { "damage_type": "stab", "amount": 15 },
    "range": 15,
    "dispersion": 75,
    "durability": 7,
    "modes": [ [ "DEFAULT", "semi-auto", 1 ], [ "AUTO", "auto", 3 ] ],
    "clip_size": 15,
    "reload": 60,
    "loudness": 18,
    "valid_mod_locations": [
      [ "accessories", 4 ],
      [ "grip", 1 ],
      [ "mechanism", 4 ],
      [ "sights", 1 ],
      [ "sling", 1 ],
      [ "stock", 1 ],
      [ "rail mount", 1 ],
      [ "underbarrel mount", 1 ]
    ],
    "pocket_data": [ { "pocket_type": "MAGAZINE", "ammo_restriction": { "pebble": 15 } } ]
  },
  {
    "id": "helsing",
    "looks_like": "ar15",
    "type": "GUN",
    "reload_noise_volume": 10,
    "symbol": "(",
    "longest_side": "800 mm",
    "color": "dark_gray",
    "name": { "str_sp": "ライフル(空圧式ﾎﾞﾙﾄﾄﾞﾗｲﾊﾞｰ)" },
    "description": "スクラップから自作した空圧式8発ボルトドライバーです。8本の銃身が回転しながら次々にボルトを発射します。とても静かで高い殺傷力があります。",
    "price": 290000,
    "price_postapoc": 12000,
    "material": [ "steel", "wood" ],
    "flags": [ "RELOAD_ONE", "STR_RELOAD", "NON_FOULING" ],
    "skill": "rifle",
    "ammo": [ "bolt" ],
    "weight": "3110 g",
    "volume": "3 L",
    "melee_damage": { "bash": 12 },
    "to_hit": -1,
    "ranged_damage": { "damage_type": "stab", "amount": 6 },
    "range": 20,
    "dispersion": 30,
    "durability": 7,
    "clip_size": 8,
    "reload": 60,
    "loudness": 22,
    "valid_mod_locations": [
      [ "accessories", 4 ],
      [ "grip", 1 ],
      [ "mechanism", 4 ],
      [ "sights", 1 ],
      [ "sling", 1 ],
      [ "stock", 1 ],
      [ "rail mount", 1 ],
      [ "underbarrel mount", 1 ]
    ],
    "pocket_data": [ { "pocket_type": "MAGAZINE", "ammo_restriction": { "bolt": 8 } } ]
  },
  {
    "id": "pneumatic_shotgun",
    "longest_side": "800 mm",
    "looks_like": "pipe_double_shotgun",
    "type": "GUN",
    "reload_noise_volume": 10,
    "symbol": "(",
    "color": "dark_gray",
    "name": { "str_sp": "ショットガン(紙筒弾/空圧式)" },
    "description": "ガラクタから自作した空圧式二連ショットガンです。一般的なショットガンよりは劣りますが、それでも十分な威力があります。ただし、標的が目の前にいる場合に限りますが。",
    "price": 220000,
    "material": [ "steel", "wood" ],
    "flags": [ "RELOAD_ONE", "STR_RELOAD", "NON_FOULING" ],
    "skill": "shotgun",
    "ammo": [ "shotcanister" ],
    "weight": "3410 g",
    "volume": "2500 ml",
    "price_postapoc": 12000,
    "melee_damage": { "bash": 8 },
    "to_hit": -1,
    "ranged_damage": { "damage_type": "stab", "amount": 15 },
    "range": 3,
    "dispersion": 350,
    "durability": 7,
    "modes": [ [ "DEFAULT", "single", 1 ], [ "DOUBLE", "double", 2 ] ],
    "clip_size": 2,
    "reload": 60,
    "loudness": 22,
    "valid_mod_locations": [
      [ "accessories", 4 ],
      [ "grip", 1 ],
      [ "mechanism", 4 ],
      [ "sights", 1 ],
      [ "sling", 1 ],
      [ "stock", 1 ],
      [ "rail mount", 1 ],
      [ "underbarrel mount", 1 ]
    ],
    "pocket_data": [ { "pocket_type": "MAGAZINE", "ammo_restriction": { "shotcanister": 2 } } ]
   }
]
